Workbook

Sheet Western Loads MW Calculations
A1: Sources
A2: 2024-2029 Western CDM Plan_signed.pdf
A3: Microsoft Word - 001a Bud Doc 2025-26 -- Operating and Capital Budget -- Draft March 27, 2025
A4: Building Info / Floor Plans - Facilities Management - Western University
A6: Hours in a year | B6: =24*365 -> 8760
A8: Building | B8: m^2 | C8: kwh/m^2 | D8: kwh (year) | E8: kw | F8: mw | G8: cost
A9: ACEB | B9: 9635 | C9: 150.04 | D9: =B9*C9 -> 1445635.4 | E9: =D9/8760 -> 165.02687 | F9: =E9/1000 -> 0.16502687 | G9: =D9*0.142 -> 205280.23
A10: Entrepreneurship | B10: 9710 | C10: 150.04 | D10: =B10*C10 -> 1456888.4 | E10: =D10/8760 -> 166.31146 | F10: =E10/1000 -> 0.16631146 | G10: =D10*0.142 -> 206878.15
A11: Health Sci | B11: 7657 | C11: 150.04 | D11: =B11*C11 -> 1148856.3 | E11: =D11/8760 -> 131.14798 | F11: =E11/1000 -> 0.13114798 | G11: =D11*0.142 -> 163137.59
A12: FIMS | B12: 12917 | C12: 150.04 | D12: =B12*C12 -> 1938066.7 | E12: =D12/8760 -> 221.24049 | F12: =E12/1000 -> 0.22124049 | G12: =D12*0.142 -> 275205.47
A13: Power Plant | B13: 2275 | C13: 150.04 | D13: =B13*C13 -> 341341 | E13: =D13/8760 -> 38.965868 | F13: =E13/1000 -> 0.038965868 | G13: =D13*0.142 -> 48470.422
A14: UC | B14: 10919 | C14: 150.04 | D14: =B14*C14 -> 1638286.8 | E14: =D14/8760 -> 187.01904 | F14: =E14/1000 -> 0.18701904 | G14: =D14*0.142 -> 232636.72
A16: Peak Load (MW) | B16: 10
A17: Savings % | B17: 0.0294
A18: Savings (MW) | B18: =B16*B17 -> 0.294
A19: Savings (kW) | B19: =B18*1000 -> 294

Sheet Dx Feeder Cost Savings
A1: Hour | B1: Price - TOU | C1: Hourly Load % of Peak | D1: Constant Z Load - Avg | G1: Constant I Load | J1: ZIP - Residential | M1: ZIP - Commerical | P1: ZIP - Average | S1: All Load Types - Average
B2: cents/kWh | C2: % | D2: MW Reduction | E2: % Reduction | F2: $ savings | G2: MW Reduction | H2: % Reduction | I2: $ savings | J2: MW Reduction | K2: % Reduction | L2: $ savings | M2: MW Reduction | N2: % Reduction | O2: $ savings | P2: MW Reduction | Q2: % Reduction | R2: $ savings | S2: MW Reduction | T2: % Reduction | U2: $ savings
A3: 1 | B3: 9.8 | C3: 0.7716 | D3: -0.41674074 | E3: 0.05400537 | F3: =D3*($B3*1000/100) -> -40.840593 | G3: -0.21522222 | H3: 0.027892989 | I3: =G3*($B3*1000/100) -> -21.091778 | J3: -0.22161243 | K3: -0.028721154 | L3: =J3*($B3*1000/100) -> -21.718018 | M3: -0.21126701 | N3: -0.02738038 | O3: =M3*($B3*1000/100) -> -20.704167 | P3: =AVERAGE(J3,M3) -> -0.21643972 | Q3: =AVERAGE(K3,N3) -> -0.028050767 | R3: =P3*($B3*1000/100) -> -21.211093 | S3: =AVERAGE(D3,G3,J3,M3) -> -0.2662106 | T3: =AVERAGE(-E3,-H3,K3,N3) -> -0.034499973 | U3: =S3*($B3*1000/100) -> -26.088639
A4: 2 | B4: 9.8 | C4: 0.7517 | D4: -0.43827778 | E4: 0.058325 | F4: =D4*($B4*1000/100) -> -42.951222 | G4: -0.227 | H4: 0.030198243 | I4: =G4*($B4*1000/100) -> -22.246 | J4: -0.232907 | K4: -0.030984036 | L4: =J4*($B4*1000/100) -> -22.824886 | M4: -0.22226572 | N4: -0.029568407 | O4: =M4*($B4*1000/100) -> -21.782041 | P4: =AVERAGE(J4,M4) -> -0.22758636 | Q4: =AVERAGE(K4,N4) -> -0.030276221 | R4: =P4*($B4*1000/100) -> -22.303463 | S4: =AVERAGE(D4,G4,J4,M4) -> -0.28011263 | T4: =AVERAGE(-E4,-H4,K4,N4) -> -0.037268921 | U4: =S4*($B4*1000/100) -> -27.451037
A5: 3 | B5: 9.8 | C5: 0.7407 | D5: -0.43455556 | E5: 0.058668889 | F5: =D5*($B5*1000/100) -> -42.586444 | G5: -0.225 | H5: 0.030376679 | I5: =G5*($B5*1000/100) -> -22.05 | J5: -0.23092087 | K5: -0.031176032 | L5: =J5*($B5*1000/100) -> -22.630245 | M5: -0.22038802 | N5: -0.029754018 | O5: =M5*($B5*1000/100) -> -21.598025 | P5: =AVERAGE(J5,M5) -> -0.22565444 | Q5: =AVERAGE(K5,N5) -> -0.030465025 | R5: =P5*($B5*1000/100) -> -22.114135 | S5: =AVERAGE(D5,G5,J5,M5) -> -0.27771611 | T5: =AVERAGE(-E5,-H5,K5,N5) -> -0.037493905 | U5: =S5*($B5*1000/100) -> -27.216179
A6: 4 | B6: 9.8 | C6: 0.7398 | D6: -0.43416667 | E6: 0.058696111 | F6: =D6*($B6*1000/100) -> -42.548333 | G6: -0.22483333 | H6: 0.030391066 | I6: =G6*($B6*1000/100) -> -22.033667 | J6: -0.23075575 | K6: -0.031191641 | L6: =J6*($B6*1000/100) -> -22.614064 | M6: -0.22023182 | N6: -0.029769104 | O6: =M6*($B6*1000/100) -> -21.582719 | P6: =AVERAGE(J6,M6) -> -0.22549379 | Q6: =AVERAGE(K6,N6) -> -0.030480373 | R6: =P6*($B6*1000/100) -> -22.098391 | S6: =AVERAGE(D6,G6,J6,M6) -> -0.27749689 | T6: =AVERAGE(-E6,-H6,K6,N6) -> -0.03751198 | U6: =S6*($B6*1000/100) -> -27.194696
A7: 5 | B7: 9.8 | C7: 0.7563 | D7: -0.44011111 | E7: 0.058182222 | F7: =D7*($B7*1000/100) -> -43.130889 | G7: -0.21277778 | H7: 0.02813407 | I7: =G7*($B7*1000/100) -> -20.852222 | J7: -0.23372433 | K7: -0.030903652 | L7: =J7*($B7*1000/100) -> -22.904984 | M7: -0.2230383 | N7: -0.029490718 | O7: =M7*($B7*1000/100) -> -21.857754 | P7: =AVERAGE(J7,M7) -> -0.22838132 | Q7: =AVERAGE(K7,N7) -> -0.030197185 | R7: =P7*($B7*1000/100) -> -22.381369 | S7: =AVERAGE(D7,G7,J7,M7) -> -0.27741288 | T7: =AVERAGE(-E7,-H7,K7,N7) -> -0.036677666 | U7: =S7*($B7*1000/100) -> -27.186462
A8: 6 | B8: 9.8 | C8: 0.7986 | D8: -0.42433333 | E8: 0.053146667 | F8: =D8*($B8*1000/100) -> -41.584667 | G8: -0.21927778 | H8: 0.027457781 | I8: =G8*($B8*1000/100) -> -21.489222 | J8: -0.22556874 | K8: -0.028245523 | L8: =J8*($B8*1000/100) -> -22.105737 | M8: -0.21498873 | N8: -0.026920703 | O8: =M8*($B8*1000/100) -> -21.068896 | P8: =AVERAGE(J8,M8) -> -0.22027874 | Q8: =AVERAGE(K8,N8) -> -0.027583113 | R8: =P8*($B8*1000/100) -> -21.587317 | S8: =AVERAGE(D8,G8,J8,M8) -> -0.27104215 | T8: =AVERAGE(-E8,-H8,K8,N8) -> -0.033942668 | U8: =S8*($B8*1000/100) -> -26.56213
A9: 7 | B9: 9.8 | C9: 0.8626 | D9: -0.44035185 | E9: 0.051048333 | F9: =D9*($B9*1000/100) -> -43.154481 | G9: -0.22737037 | H9: 0.026358772 | I9: =G9*($B9*1000/100) -> -22.282296 | J9: -0.23388322 | K9: -0.02711375 | L9: =J9*($B9*1000/100) -> -22.920556 | M9: -0.22257365 | N9: -0.025802648 | O9: =M9*($B9*1000/100) -> -21.812218 | P9: =AVERAGE(J9,M9) -> -0.22822844 | Q9: =AVERAGE(K9,N9) -> -0.026458199 | R9: =P9*($B9*1000/100) -> -22.366387 | S9: =AVERAGE(D9,G9,J9,M9) -> -0.28104477 | T9: =AVERAGE(-E9,-H9,K9,N9) -> -0.032580876 | U9: =S9*($B9*1000/100) -> -27.542388
A10: 8 | B10: 20.3 | C10: 0.9059 | D10: -0.41414815 | E10: 0.045731667 | F10: =D10*($B10*1000/100) -> -84.072074 | G10: -0.21412963 | H10: 0.023637228 | I10: =G10*($B10*1000/100) -> -43.468315 | J10: -0.21981209 | K10: -0.024264499 | L10: =J10*($B10*1000/100) -> -44.621855 | M10: -0.20905853 | N10: -0.02307744 | O10: =M10*($B10*1000/100) -> -42.438882 | P10: =AVERAGE(J10,M10) -> -0.21443531 | Q10: =AVERAGE(K10,N10) -> -0.023670969 | R10: =P10*($B10*1000/100) -> -43.530368 | S10: =AVERAGE(D10,G10,J10,M10) -> -0.2642871 | T10: =AVERAGE(-E10,-H10,K10,N10) -> -0.029177708 | U10: =S10*($B10*1000/100) -> -53.650281
A11: 9 | B11: 20.3 | C11: 0.9181 | D11: -0.4107037 | E11: 0.04473463 | F11: =D11*($B11*1000/100) -> -83.372852 | G11: -0.19557407 | H11: 0.021302019 | I11: =G11*($B11*1000/100) -> -39.701537 | J11: -0.21777072 | K11: -0.023719717 | L11: =J11*($B11*1000/100) -> -44.207456 | M11: -0.20229977 | N11: -0.022034612 | O11: =M11*($B11*1000/100) -> -41.066854 | P11: =AVERAGE(J11,M11) -> -0.21003524 | Q11: =AVERAGE(K11,N11) -> -0.022877165 | R11: =P11*($B11*1000/100) -> -42.637155 | S11: =AVERAGE(D11,G11,J11,M11) -> -0.25658707 | T11: =AVERAGE(-E11,-H11,K11,N11) -> -0.027947745 | U11: =S11*($B11*1000/100) -> -52.087175
A12: 10 | B12: 20.3 | C12: 0.923 | D12: -0.39412963 | E12: 0.042697963 | F12: =D12*($B12*1000/100) -> -80.008315 | G12: -0.19255556 | H12: 0.020861875 | I12: =G12*($B12*1000/100) -> -39.088778 | J12: -0.20860999 | K12: -0.0226013 | L12: =J12*($B12*1000/100) -> -42.347827 | M12: -0.19108255 | N12: -0.020702336 | O12: =M12*($B12*1000/100) -> -38.789757 | P12: =AVERAGE(J12,M12) -> -0.19984627 | Q12: =AVERAGE(K12,N12) -> -0.021651818 | R12: =P12*($B12*1000/100) -> -40.568792 | S12: =AVERAGE(D12,G12,J12,M12) -> -0.24659443 | T12: =AVERAGE(-E12,-H12,K12,N12) -> -0.026715868 | U12: =S12*($B12*1000/100) -> -50.058669
A13: 11 | B13: 20.3 | C13: 0.9261 | D13: -0.37181481 | E13: 0.040152222 | F13: =D13*($B13*1000/100) -> -75.478407 | G13: -0.18987037 | H13: 0.020502112 | I13: =G13*($B13*1000/100) -> -38.543685 | J13: -0.19698599 | K13: -0.021270488 | L13: =J13*($B13*1000/100) -> -39.988155 | M13: -0.1874061 | N13: -0.020236055 | O13: =M13*($B13*1000/100) -> -38.043438 | P13: =AVERAGE(J13,M13) -> -0.19219604 | Q13: =AVERAGE(K13,N13) -> -0.020753272 | R13: =P13*($B13*1000/100) -> -39.015797 | S13: =AVERAGE(D13,G13,J13,M13) -> -0.23651932 | T13: =AVERAGE(-E13,-H13,K13,N13) -> -0.025540219 | U13: =S13*($B13*1000/100) -> -48.013421
A14: 12 | B14: 15.7 | C14: 0.9292 | D14: -0.36681481 | E14: 0.039469815 | F14: =D14*($B14*1000/100) -> -57.589926 | G14: -0.18711111 | H14: 0.020136777 | I14: =G14*($B14*1000/100) -> -29.376444 | J14: -0.19424624 | K14: -0.020904675 | L14: =J14*($B14*1000/100) -> -30.49666 | M14: -0.18274192 | N14: -0.019666587 | O14: =M14*($B14*1000/100) -> -28.690482 | P14: =AVERAGE(J14,M14) -> -0.18849408 | Q14: =AVERAGE(K14,N14) -> -0.020285631 | R14: =P14*($B14*1000/100) -> -29.593571 | S14: =AVERAGE(D14,G14,J14,M14) -> -0.23272852 | T14: =AVERAGE(-E14,-H14,K14,N14) -> -0.025044464 | U14: =S14*($B14*1000/100) -> -36.538378
... A26: 24 | B26: 9.8 | C26: 0.8047 | D26: -0.42611111 | E26: 0.052952778 | F26: =D26*($B26*1000/100) -> -41.758889 | G26: -0.22027778 | H26: 0.027373892 | I26: =G26*($B26*1000/100) -> -21.587222 | J26: -0.22642204 | K26: -0.028137448 | L26: =J26*($B26*1000/100) -> -22.18936 | M26: -0.21579157 | N26: -0.0268164 | O26: =M26*($B26*1000/100) -> -21.147574 | P26: =AVERAGE(J26,M26) -> -0.22110681 | Q26: =AVERAGE(K26,N26) -> -0.027476924 | R26: =P26*($B26*1000/100) -> -21.668467 | S26: =AVERAGE(D26,G26,J26,M26) -> -0.27215063 | T26: =AVERAGE(-E26,-H26,K26,N26) -> -0.03382013 | U26: =S26*($B26*1000/100) -> -26.670761
A27: Total daily savings | D27: Using tiered | F27: =SUM(F3:F26) -> -1327.5841 | I27: =SUM(I3:I26) -> -677.28854 | L27: =SUM(L3:L26) -> -704.32282 | O27: =SUM(O3:O26) -> -667.02941 | R27: =SUM(R3:R26) -> -685.67612 | U27: =SUM(U3:U26) -> -844.05623
A28: Average annualized savings | D28: =SUM(D3:D26)*1000*365*0.142 -> -501371.75 | F28: =F27*364 -> -483240.62 | G28: =SUM(G3:G26)*1000*365*0.142 -> -256280.15 | I28: =I27*364 -> -246533.03 | J28: =SUM(J3:J26)*1000*365*0.142 -> -266069.94 | L28: =L27*364 -> -256373.51 | M28: =SUM(M3:M26)*1000*365*0.142 -> -252396.33 | O28: =O27*364 -> -242798.71 | P28: =SUM(P3:P26)*1000*365*0.142 -> -259233.13 | R28: =R27*364 -> -249586.11 | S28: =SUM(S3:S26)*1000*365*0.142 -> -319029.54 | U28: =U27*364 -> -307236.47
A30: *Note that these values are the AVERAGE of all simulations done for that load type | S30: Average | T30: =AVERAGE(T3:T26) -> -0.02935845
A31: *We can make more graphs and cost savings calculations with more filters (such as specific PV bus, specific PF, etc) | F31: Load Type | G31: Constant Z Load | H31: Constant I Load | I31: ZIP - Res. | J31: ZIP - Comm. | K31: Zip - Average | L31: All Load Types Average
F32: Total daily savings | G32: =F27 -> -1327.5841 | H32: =I27 -> -677.28854 | I32: =L27 -> -704.32282 | J32: =O27 -> -667.02941 | K32: =R27 -> -685.67612 | L32: =U27 -> -844.05623
A33: Electricity rates | Ontario Energy Board | F33: Average annualized savings | G33: =F28 -> -483240.62 | H33: =I28 -> -246533.03 | I33: =L28 -> -256373.51 | J33: =O28 -> -242798.71 | K33: =R28 -> -249586.11 | L33: =U28 -> -307236.47

Sheet IEEE 14-Bus Cost Savings
A1: Hour | B1: Price - TOU | C1: Hourly Load % of Peak | D1: Two Small + 1 Medium PV Farms | G1: Two Small + 1 Medium PV Farms | J1: Two Small + 1 Medium PV Farms | M1: One large PV Farm | P1: One large PV Farm | S1: One large PV Farm | V1: Three small PV Farms | Y1: Three small PV Farms | AB1: Three small PV Farms | AE1: All Load Types - Average | AH1: All Load Types - Average | AK1: All Load Types - Average
D2: Bus 4 = 52.632 MVAR | G2: Bus 9 = 10.526 MVAR | J2: Bus 14 = 10.526 MVAR | M2: Bus 4 = 105.263 MVAR | P2: Bus 9 = 0 MVAR | S2: Bus 14 = 0 MVAR | V2: Bus 4 = 10.526 MVAR | Y2: Bus 9 = 10.526 MVAR | AB2: Bus 14 = 10.526 MVAR | AE2: Bus 4 | AH2: Bus 9 | AK2: Bus 14
B3: cents/kWh | C3: % | D3: MW Reduction | E3: % Reduction | F3: $ savings | G3: MW Reduction | H3: % Reduction | I3: $ savings | J3: MW Reduction | K3: % Reduction | L3: $ savings | M3: MW Reduction | N3: % Reduction | O3: $ savings | P3: MW Reduction | Q3: % Reduction | R3: $ savings | S3: MW Reduction | T3: % Reduction | U3: $ savings | V3: MW Reduction | W3: % Reduction | X3: $ savings | Y3: MW Reduction | Z3: % Reduction | AA3: $ savings | AB3: MW Reduction | AC3: % Reduction | AD3: $ savings | AE3: MW Reduction | AF3: % Reduction | AG3: $ savings | AH3: MW Reduction | AI3: % Reduction | AJ3: $ savings | AK3: MW Reduction | AL3: % Reduction | AM3: $ savings
A4: 1 | B4: 9.8 | C4: 0.7716 | D4: ='IEEE 14-bus MW reduction data'!H4 -> -1.0922928 | F4: =D4*($B4*1000/100) -> -107.04469 | G4: ='IEEE 14-bus MW reduction data'!I4 -> -0.63070107 | I4: =G4*($B4*1000/100) -> -61.808704 | J4: ='IEEE 14-bus MW reduction data'!J4 -> -0.40576458 | L4: =J4*($B4*1000/100) -> -39.764929 | M4: ='IEEE 14-bus MW reduction data'!Q4 -> -1.7340508 | O4: =M4*($B4*1000/100) -> -169.93697 | P4: ='IEEE 14-bus MW reduction data'!R4 -> -0.41671371 | R4: =P4*($B4*1000/100) -> -40.837944 | S4: ='IEEE 14-bus MW reduction data'!S4 -> -0.13124752 | U4: =S4*($B4*1000/100) -> -12.862257 | V4: ='IEEE 14-bus MW reduction data'!Z4 -> -0.38977051 | X4: =V4*($B4*1000/100) -> -38.19751 | Y4: ='IEEE 14-bus MW reduction data'!AA4 -> -0.44854736 | AA4: =Y4*($B4*1000/100) -> -43.957642 | AB4: ='IEEE 14-bus MW reduction data'!AB4 -> -0.34740257 | AD4: =AB4*($B4*1000/100) -> -34.045452 | AE4: =AVERAGE(V4,M4,D4) -> -1.072038 | AG4: =AE4*($B4*1000/100) -> -105.05973 | AH4: =AVERAGE(Y4,P4,G4) -> -0.49865405 | AJ4: =AH4*($B4*1000/100) -> -48.868097 | AK4: =AVERAGE(AB4,S4,J4) -> -0.29480489 | AM4: =AK4*($B4*1000/100) -> -28.890879
A5: 2 | B5: 9.8 | C5: 0.7517 | D5: ='IEEE 14-bus MW reduction data'!H5 -> -1.0630608 | F5: =D5*($B5*1000/100) -> -104.17995 | G5: ='IEEE 14-bus MW reduction data'!I5 -> -0.61417198 | I5: =G5*($B5*1000/100) -> -60.188854 | J5: ='IEEE 14-bus MW reduction data'!J5 -> -0.39499569 | L5: =J5*($B5*1000/100) -> -38.709578 | M5: ='IEEE 14-bus MW reduction data'!Q5 -> -1.7135658 | O5: =M5*($B5*1000/100) -> -167.92945 | P5: ='IEEE 14-bus MW reduction data'!R5 -> -0.41269302 | R5: =P5*($B5*1000/100) -> -40.443916 | S5: ='IEEE 14-bus MW reduction data'!S5 -> -0.13017178 | U5: =S5*($B5*1000/100) -> -12.756834 | V5: ='IEEE 14-bus MW reduction data'!Z5 -> -0.37919235 | X5: =V5*($B5*1000/100) -> -37.160851 | Y5: ='IEEE 14-bus MW reduction data'!AA5 -> -0.4367466 | AA5: =Y5*($B5*1000/100) -> -42.801167 | AB5: ='IEEE 14-bus MW reduction data'!AB5 -> -0.33810616 | AD5: =AB5*($B5*1000/100) -> -33.134403 | AE5: =AVERAGE(V5,M5,D5) -> -1.0519396 | AG5: =AE5*($B5*1000/100) -> -103.09009 | AH5: =AVERAGE(Y5,P5,G5) -> -0.48787053 | AJ5: =AH5*($B5*1000/100) -> -47.811312 | AK5: =AVERAGE(AB5,S5,J5) -> -0.28775787 | AM5: =AK5*($B5*1000/100) -> -28.200272
A6: 3 | B6: 9.8 | C6: 0.7407 | D6: ='IEEE 14-bus MW reduction data'!H6 -> -1.0434532 | F6: =D6*($B6*1000/100) -> -102.25842 | G6: ='IEEE 14-bus MW reduction data'!I6 -> -0.60416031 | I6: =G6*($B6*1000/100) -> -59.20771 | J6: ='IEEE 14-bus MW reduction data'!J6 -> -0.38877487 | L6: =J6*($B6*1000/100) -> -38.099937 | M6: ='IEEE 14-bus MW reduction data'!Q6 -> -1.6980247 | O6: =M6*($B6*1000/100) -> -166.40643 | P6: ='IEEE 14-bus MW reduction data'!R6 -> -0.40924263 | R6: =P6*($B6*1000/100) -> -40.105778 | S6: ='IEEE 14-bus MW reduction data'!S6 -> -0.1291151 | U6: =S6*($B6*1000/100) -> -12.65328 | V6: ='IEEE 14-bus MW reduction data'!Z6 -> -0.36986923 | X6: =V6*($B6*1000/100) -> -36.247185 | Y6: ='IEEE 14-bus MW reduction data'!AA6 -> -0.42936134 | AA6: =Y6*($B6*1000/100) -> -42.077412 | AB6: ='IEEE 14-bus MW reduction data'!AB6 -> -0.33272171 | AD6: =AB6*($B6*1000/100) -> -32.606728 | AE6: =AVERAGE(V6,M6,D6) -> -1.0371157 | AG6: =AE6*($B6*1000/100) -> -101.63734 | AH6: =AVERAGE(Y6,P6,G6) -> -0.48092143 | AJ6: =AH6*($B6*1000/100) -> -47.1303 | AK6: =AVERAGE(AB6,S6,J6) -> -0.28353723 | AM6: =AK6*($B6*1000/100) -> -27.786648
A7: 4 | B7: 9.8 | C7: 0.7398 | D7: ='IEEE 14-bus MW reduction data'!H7 -> -1.0418587 | F7: =D7*($B7*1000/100) -> -102.10215 | G7: ='IEEE 14-bus MW reduction data'!I7 -> -0.60334206 | I7: =G7*($B7*1000/100) -> -59.127522 | J7: ='IEEE 14-bus MW reduction data'!J7 -> -0.38826752 | L7: =J7*($B7*1000/100) -> -38.050217 | M7: ='IEEE 14-bus MW reduction data'!Q7 -> -1.6967354 | O7: =M7*($B7*1000/100) -> -166.28007 | P7: ='IEEE 14-bus MW reduction data'!R7 -> -0.40895653 | R7: =P7*($B7*1000/100) -> -40.07774 | S7: ='IEEE 14-bus MW reduction data'!S7 -> -0.12902832 | U7: =S7*($B7*1000/100) -> -12.644775 | V7: ='IEEE 14-bus MW reduction data'!Z7 -> -0.36910248 | X7: =V7*($B7*1000/100) -> -36.172043 | Y7: ='IEEE 14-bus MW reduction data'!AA7 -> -0.42875862 | AA7: =Y7*($B7*1000/100) -> -42.018345 | AB7: ='IEEE 14-bus MW reduction data'!AB7 -> -0.33228016 | AD7: =AB7*($B7*1000/100) -> -32.563456 | AE7: =AVERAGE(V7,M7,D7) -> -1.0358988 | AG7: =AE7*($B7*1000/100) -> -101.51809 | AH7: =AVERAGE(Y7,P7,G7) -> -0.4803524 | AJ7: =AH7*($B7*1000/100) -> -47.074535 | AK7: =AVERAGE(AB7,S7,J7) -> -0.283192 | AM7: =AK7*($B7*1000/100) -> -27.752816
A8: 5 | B8: 9.8 | C8: 0.7563 | D8: ='IEEE 14-bus MW reduction data'!H8 -> -1.0702515 | F8: =D8*($B8*1000/100) -> -104.88464 | G8: ='IEEE 14-bus MW reduction data'!I8 -> -0.61810493 | I8: =G8*($B8*1000/100) -> -60.574284 | J8: ='IEEE 14-bus MW reduction data'!J8 -> -0.39751625 | L8: =J8*($B8*1000/100) -> -38.956593 | M8: ='IEEE 14-bus MW reduction data'!Q8 -> -1.718895 | O8: =M8*($B8*1000/100) -> -168.45171 | P8: ='IEEE 14-bus MW reduction data'!R8 -> -0.41383362 | R8: =P8*($B8*1000/100) -> -40.555695 | S8: ='IEEE 14-bus MW reduction data'!S8 -> -0.13051319 | U8: =S8*($B8*1000/100) -> -12.790293 | V8: ='IEEE 14-bus MW reduction data'!Z8 -> -0.38206482 | X8: =V8*($B8*1000/100) -> -37.442352 | Y8: ='IEEE 14-bus MW reduction data'!AA8 -> -0.43957138 | AA8: =Y8*($B8*1000/100) -> -43.077995 | AB8: ='IEEE 14-bus MW reduction data'!AB8 -> -0.34027576 | AD8: =AB8*($B8*1000/100) -> -33.347025 | AE8: =AVERAGE(V8,M8,D8) -> -1.0570704 | AG8: =AE8*($B8*1000/100) -> -103.5929 | AH8: =AVERAGE(Y8,P8,G8) -> -0.49050331 | AJ8: =AH8*($B8*1000/100) -> -48.069324 | AK8: =AVERAGE(AB8,S8,J8) -> -0.28943507 | AM8: =AK8*($B8*1000/100) -> -28.364637
A9: 6 | B9: 9.8 | C9: 0.7986 | D9: ='IEEE 14-bus MW reduction data'!H9 -> -1.1311798 | F9: =D9*($B9*1000/100) -> -110.85562 | G9: ='IEEE 14-bus MW reduction data'!I9 -> -0.65290451 | I9: =G9*($B9*1000/100) -> -63.984642 | J9: ='IEEE 14-bus MW reduction data'!J9 -> -0.42031288 | L9: =J9*($B9*1000/100) -> -41.190662 | M9: ='IEEE 14-bus MW reduction data'!Q9 -> -1.7583847 | O9: =M9*($B9*1000/100) -> -172.3217 | P9: ='IEEE 14-bus MW reduction data'!R9 -> -0.42201996 | R9: =P9*($B9*1000/100) -> -41.357956 | S9: ='IEEE 14-bus MW reduction data'!S9 -> -0.13310814 | U9: =S9*($B9*1000/100) -> -13.044598 | V9: ='IEEE 14-bus MW reduction data'!Z9 -> -0.40315628 | X9: =V9*($B9*1000/100) -> -39.509315 | Y9: ='IEEE 14-bus MW reduction data'!AA9 -> -0.46429443 | AA9: =Y9*($B9*1000/100) -> -45.500854 | AB9: ='IEEE 14-bus MW reduction data'!AB9 -> -0.35992908 | AD9: =AB9*($B9*1000/100) -> -35.27305 | AE9: =AVERAGE(V9,M9,D9) -> -1.0975736 | AG9: =AE9*($B9*1000/100) -> -107.56221 | AH9: =AVERAGE(Y9,P9,G9) -> -0.51307297 | AJ9: =AH9*($B9*1000/100) -> -50.281151 | AK9: =AVERAGE(AB9,S9,J9) -> -0.30445004 | AM9: =AK9*($B9*1000/100) -> -29.836103
A10: 7 | B10: 9.8 | C10: 0.8626 | D10: ='IEEE 14-bus MW reduction data'!H10 -> -1.2647362 | F10: =D10*($B10*1000/100) -> -123.94415 | G10: ='IEEE 14-bus MW reduction data'!I10 -> -0.71594334 | I10: =G10*($B10*1000/100) -> -70.162447 | J10: ='IEEE 14-bus MW reduction data'!J10 -> -0.45800209 | L10: =J10*($B10*1000/100) -> -44.884205 | M10: ='IEEE 14-bus MW reduction data'!Q10 -> -1.8033867 | O10: =M10*($B10*1000/100) -> -176.7319 | P10: ='IEEE 14-bus MW reduction data'!R10 -> -0.43034172 | R10: =P10*($B10*1000/100) -> -42.173489 | S10: ='IEEE 14-bus MW reduction data'!S10 -> -0.13557529 | U10: =S10*($B10*1000/100) -> -13.286379 | V10: ='IEEE 14-bus MW reduction data'!Z10 -> -0.43453407 | X10: =V10*($B10*1000/100) -> -42.584339 | Y10: ='IEEE 14-bus MW reduction data'!AA10 -> -0.50111961 | AA10: =Y10*($B10*1000/100) -> -49.109722 | AB10: ='IEEE 14-bus MW reduction data'!AB10 -> -0.38932037 | AD10: =AB10*($B10*1000/100) -> -38.153397 | AE10: =AVERAGE(V10,M10,D10) -> -1.1675523 | AG10: =AE10*($B10*1000/100) -> -114.42013 | AH10: =AVERAGE(Y10,P10,G10) -> -0.54913489 | AJ10: =AH10*($B10*1000/100) -> -53.815219 | AK10: =AVERAGE(AB10,S10,J10) -> -0.32763259 | AM10: =AK10*($B10*1000/100) -> -32.107993
A11: 8 | B11: 20.3 | C11: 0.9059 | D11: ='IEEE 14-bus MW reduction data'!H11 -> -1.3754578 | F11: =D11*($B11*1000/100) -> -279.21793 | G11: ='IEEE 14-bus MW reduction data'!I11 -> -0.75827408 | I11: =G11*($B11*1000/100) -> -153.92964 | J11: ='IEEE 14-bus MW reduction data'!J11 -> -0.48037004 | L11: =J11*($B11*1000/100) -> -97.515119 | M11: ='IEEE 14-bus MW reduction data'!Q11 -> -1.823288 | O11: =M11*($B11*1000/100) -> -370.12746 | P11: ='IEEE 14-bus MW reduction data'!R11 -> -0.43325424 | R11: =P11*($B11*1000/100) -> -87.950611 | S11: ='IEEE 14-bus MW reduction data'!S11 -> -0.13638115 | U11: =S11*($B11*1000/100) -> -27.685373 | V11: ='IEEE 14-bus MW reduction data'!Z11 -> -0.45157051 | X11: =V11*($B11*1000/100) -> -91.668814 | Y11: ='IEEE 14-bus MW reduction data'!AA11 -> -0.51922226 | AA11: =Y11*($B11*1000/100) -> -105.40212 | AB11: ='IEEE 14-bus MW reduction data'!AB11 -> -0.40393877 | AD11: =AB11*($B11*1000/100) -> -81.99957 | AE11: =AVERAGE(V11,M11,D11) -> -1.2167721 | AG11: =AE11*($B11*1000/100) -> -247.00473 | AH11: =AVERAGE(Y11,P11,G11) -> -0.57025019 | AJ11: =AH11*($B11*1000/100) -> -115.76079 | AK11: =AVERAGE(AB11,S11,J11) -> -0.34022999 | AM11: =AK11*($B11*1000/100) -> -69.066688
A12: 9 | B12: 20.3 | C12: 0.9181 | D12: ='IEEE 14-bus MW reduction data'!H12 -> -1.3537178 | F12: =D12*($B12*1000/100) -> -274.80471 | G12: ='IEEE 14-bus MW reduction data'!I12 -> -0.74002934 | I12: =G12*($B12*1000/100) -> -150.22596 | J12: ='IEEE 14-bus MW reduction data'!J12 -> -0.46807146 | L12: =J12*($B12*1000/100) -> -95.018507 | M12: ='IEEE 14-bus MW reduction data'!Q12 -> -1.8273048 | O12: =M12*($B12*1000/100) -> -370.94288 | P12: ='IEEE 14-bus MW reduction data'!R12 -> -0.43366432 | R12: =P12*($B12*1000/100) -> -88.033857 | S12: ='IEEE 14-bus MW reduction data'!S12 -> -0.13648176 | U12: =S12*($B12*1000/100) -> -27.705798 | V12: ='IEEE 14-bus MW reduction data'!Z12 -> -0.44458389 | X12: =V12*($B12*1000/100) -> -90.25053 | Y12: ='IEEE 14-bus MW reduction data'!AA12 -> -0.50504112 | AA12: =Y12*($B12*1000/100) -> -102.52335 | AB12: ='IEEE 14-bus MW reduction data'!AB12 -> -0.39300823 | AD12: =AB12*($B12*1000/100) -> -79.780671 | AE12: =AVERAGE(V12,M12,D12) -> -1.2085355 | AG12: =AE12*($B12*1000/100) -> -245.33271 | AH12: =AVERAGE(Y12,P12,G12) -> -0.55957826 | AJ12: =AH12*($B12*1000/100) -> -113.59439 | AK12: =AVERAGE(AB12,S12,J12) -> -0.33252048 | AM12: =AK12*($B12*1000/100) -> -67.501658
A13: 10 | B13: 20.3 | C13: 0.923 | D13: ='IEEE 14-bus MW reduction data'!H13 -> -1.2863255 | F13: =D13*($B13*1000/100) -> -261.12407 | G13: ='IEEE 14-bus MW reduction data'!I13 -> -0.69973087 | I13: =G13*($B13*1000/100) -> -142.04537 | J13: ='IEEE 14-bus MW reduction data'!J13 -> -0.44289875 | L13: =J13*($B13*1000/100) -> -89.908446 | M13: ='IEEE 14-bus MW reduction data'!Q13 -> -1.8287201 | O13: =M13*($B13*1000/100) -> -371.23018 | P13: ='IEEE 14-bus MW reduction data'!R13 -> -0.433568 | R13: =P13*($B13*1000/100) -> -88.014304 | S13: ='IEEE 14-bus MW reduction data'!S13 -> -0.13631201 | U13: =S13*($B13*1000/100) -> -27.671338 | V13: ='IEEE 14-bus MW reduction data'!Z13 -> -0.42890549 | X13: =V13*($B13*1000/100) -> -87.067814 | Y13: ='IEEE 14-bus MW reduction data'!AA13 -> -0.47835064 | AA13: =Y13*($B13*1000/100) -> -97.10518 | AB13: ='IEEE 14-bus MW reduction data'!AB13 -> -0.37223768 | AD13: =AB13*($B13*1000/100) -> -75.56425 | AE13: =AVERAGE(V13,M13,D13) -> -1.181317 | AG13: =AE13*($B13*1000/100) -> -239.80735 | AH13: =AVERAGE(Y13,P13,G13) -> -0.5372165 | AJ13: =AH13*($B13*1000/100) -> -109.05495 | AK13: =AVERAGE(AB13,S13,J13) -> -0.31714948 | AM13: =AK13*($B13*1000/100) -> -64.381344
A14: 11 | B14: 20.3 | C14: 0.9261 | D14: ='IEEE 14-bus MW reduction data'!H14 -> -1.2110367 | F14: =D14*($B14*1000/100) -> -245.84045 | G14: ='IEEE 14-bus MW reduction data'!I14 -> -0.65595531 | I14: =G14*($B14*1000/100) -> -133.15893 | J14: ='IEEE 14-bus MW reduction data'!J14 -> -0.41576147 | L14: =J14*($B14*1000/100) -> -84.399579 | M14: ='IEEE 14-bus MW reduction data'!Q14 -> -1.812767 | O14: =M14*($B14*1000/100) -> -367.99171 | P14: ='IEEE 14-bus MW reduction data'!R14 -> -0.42949295 | R14: =P14*($B14*1000/100) -> -87.187069 | S14: ='IEEE 14-bus MW reduction data'!S14 -> -0.13514853 | U14: =S14*($B14*1000/100) -> -27.435151 | V14: ='IEEE 14-bus MW reduction data'!Z14 -> -0.41181564 | X14: =V14*($B14*1000/100) -> -83.598576 | Y14: ='IEEE 14-bus MW reduction data'!AA14 -> -0.44978428 | AA14: =Y14*($B14*1000/100) -> -91.306209 | AB14: ='IEEE 14-bus MW reduction data'!AB14 -> -0.35000038 | AD14: =AB14*($B14*1000/100) -> -71.050077 | AE14: =AVERAGE(V14,M14,D14) -> -1.1452065 | AG14: =AE14*($B14*1000/100) -> -232.47691 | AH14: =AVERAGE(Y14,P14,G14) -> -0.51174418 | AJ14: =AH14*($B14*1000/100) -> -103.88407 | AK14: =AVERAGE(AB14,S14,J14) -> -0.30030346 | AM14: =AK14*($B14*1000/100) -> -60.961602
A15: 12 | B15: 15.7 | C15: 0.9292 | D15: ='IEEE 14-bus MW reduction data'!H15 -> -1.1722813 | F15: =D15*($B15*1000/100) -> -184.04816 | G15: ='IEEE 14-bus MW reduction data'!I15 -> -0.63263416 | I15: =G15*($B15*1000/100) -> -99.323564 | J15: ='IEEE 14-bus MW reduction data'!J15 -> -0.40115738 | L15: =J15*($B15*1000/100) -> -62.981709 | M15: ='IEEE 14-bus MW reduction data'!Q15 -> -1.7346878 | O15: =M15*($B15*1000/100) -> -272.34599 | P15: ='IEEE 14-bus MW reduction data'!R15 -> -0.40913105 | R15: =P15*($B15*1000/100) -> -64.233575 | S15: ='IEEE 14-bus MW reduction data'!S15 -> -0.1287365 | U15: =S15*($B15*1000/100) -> -20.21163 | V15: ='IEEE 14-bus MW reduction data'!Z15 -> -0.40265274 | X15: =V15*($B15*1000/100) -> -63.21648 | Y15: ='IEEE 14-bus MW reduction data'!AA15 -> -0.434165 | AA15: =Y15*($B15*1000/100) -> -68.163905 | AB15: ='IEEE 14-bus MW reduction data'!AB15 -> -0.33786392 | AD15: =AB15*($B15*1000/100) -> -53.044636 | AE15: =AVERAGE(V15,M15,D15) -> -1.1032073 | AG15: =AE15*($B15*1000/100) -> -173.20354 | AH15: =AVERAGE(Y15,P15,G15) -> -0.49197674 | AJ15: =AH15*($B15*1000/100) -> -77.240348 | AK15: =AVERAGE(AB15,S15,J15) -> -0.2892526 | AM15: =AK15*($B15*1000/100) -> -45.412658
... A26: 23 | B26: 9.8 | C26: 0.8547 | D26: ='IEEE 14-bus MW reduction data'!H26 -> -1.2431526 | F26: =D26*($B26*1000/100) -> -121.82896 | G26: ='IEEE 14-bus MW reduction data'!I26 -> -0.70721436 | I26: =G26*($B26*1000/100) -> -69.307007 | J26: ='IEEE 14-bus MW reduction data'!J26 -> -0.45324612 | L26: =J26*($B26*1000/100) -> -44.418119 | M26: ='IEEE 14-bus MW reduction data'!Q26 -> -1.7988167 | O26: =M26*($B26*1000/100) -> -176.28403 | P26: ='IEEE 14-bus MW reduction data'!R26 -> -0.42957115 | R26: =P26*($B26*1000/100) -> -42.097973 | S26: ='IEEE 14-bus MW reduction data'!S26 -> -0.13535023 | U26: =S26*($B26*1000/100) -> -13.264322 | V26: ='IEEE 14-bus MW reduction data'!Z26 -> -0.43095016 | X26: =V26*($B26*1000/100) -> -42.233116 | Y26: ='IEEE 14-bus MW reduction data'!AA26 -> -0.49702835 | AA26: =Y26*($B26*1000/100) -> -48.708778 | AB26: ='IEEE 14-bus MW reduction data'!AB26 -> -0.38604259 | AD26: =AB26*($B26*1000/100) -> -37.832174 | AE26: =AVERAGE(V26,M26,D26) -> -1.1576398 | AG26: =AE26*($B26*1000/100) -> -113.4487 | AH26: =AVERAGE(Y26,P26,G26) -> -0.54460462 | AJ26: =AH26*($B26*1000/100) -> -53.371253 | AK26: =AVERAGE(AB26,S26,J26) -> -0.32487965 | AM26: =AK26*($B26*1000/100) -> -31.838205
A27: 24 | B27: 9.8 | C27: 0.8047 | D27: ='IEEE 14-bus MW reduction data'!H27 -> -1.1399803 | F27: =D27*($B27*1000/100) -> -111.71807 | G27: ='IEEE 14-bus MW reduction data'!I27 -> -0.65792274 | I27: =G27*($B27*1000/100) -> -64.476429 | J27: ='IEEE 14-bus MW reduction data'!J27 -> -0.42360687 | L27: =J27*($B27*1000/100) -> -41.513474 | M27: ='IEEE 14-bus MW reduction data'!Q27 -> -1.7634506 | O27: =M27*($B27*1000/100) -> -172.81816 | R27: =P27*($B27*1000/100) -> 0 | S27: ='IEEE 14-bus MW reduction data'!S27 -> -0.1334095 | U27: =S27*($B27*1000/100) -> -13.074131 | V27: ='IEEE 14-bus MW reduction data'!Z27 -> -0.40618896 | X27: =V27*($B27*1000/100) -> -39.806519 | Y27: ='IEEE 14-bus MW reduction data'!AA27 -> -0.46785164 | AA27: =Y27*($B27*1000/100) -> -45.849461 | AB27: ='IEEE 14-bus MW reduction data'!AB27 -> -0.36276913 | AD27: =AB27*($B27*1000/100) -> -35.551374 | AE27: =AVERAGE(V27,M27,D27) -> -1.1032066 | AG27: =AE27*($B27*1000/100) -> -108.11425 | AH27: =AVERAGE(Y27,P27,G27) -> -0.56288719 | AJ27: =AH27*($B27*1000/100) -> -55.162945 | AK27: =AVERAGE(AB27,S27,J27) -> -0.30659517 | AM27: =AK27*($B27*1000/100) -> -30.046326
A28: Total daily savings | F28: =SUM(F4:F27) -> -4441.7129 | I28: =SUM(I4:I27) -> -2420.7566 | L28: =SUM(L4:L27) -> -1529.1717 | O28: =SUM(O4:O27) -> -5998.4517 | R28: =SUM(R4:R27) -> -1382.2571 | U28: =SUM(U4:U27) -> -448.04755 | X28: =SUM(X4:X27) -> -1464.0127 | AA28: =SUM(AA4:AA27) -> -1650.872 | AD28: =SUM(AD4:AD27) -> -1283.2154 | AG28: =SUM(AG4:AG27) -> -3968.0591 | AJ28: =SUM(AJ4:AJ27) -> -1836.3496 | AM28: =SUM(AM4:AM27) -> -1086.8115
A29: Average annualized savings | D29: =SUM(D4:D27)*1000*365*0.142 -> -1622710.6 | F29: =F28*365 -> -1621225.2 | G29: =SUM(G4:G27)*1000*365*0.142 -> -890550.33 | I29: =I28*365 -> -883576.17 | J29: =SUM(J4:J27)*1000*365*0.142 -> -563774.3 | L29: =L28*365 -> -558147.66 | M29: =SUM(M4:M27)*1000*365*0.142 -> -2226370.2 | O29: =O28*365 -> -2189434.9 | P29: =SUM(P4:P27)*1000*365*0.142 -> -507373.83 | R29: =R28*365 -> -504523.84 | S29: =SUM(S4:S27)*1000*365*0.142 -> -166618.28 | U29: =U28*365 -> -163537.36 | V29: =SUM(V4:V27)*1000*365*0.142 -> -538516.04 | X29: =X28*365 -> -534364.64 | Y29: =SUM(Y4:Y27)*1000*365*0.142 -> -610131.8 | AA29: =AA28*365 -> -602568.28 | AB29: =SUM(AB4:AB27)*1000*365*0.142 -> -474156.82 | AD29: =AD28*365 -> -468373.61 | AE29: =SUM(AE4:AE27)*1000*365*0.142 -> -1462532.3 | AG29: =AG28*365 -> -1448341.6 | AH29: =SUM(AH4:AH27)*1000*365*0.142 -> -679076.8 | AJ29: =AJ28*365 -> -670267.59 | AK29: =SUM(AK4:AK27)*1000*365*0.142 -> -401516.47 | AM29: =AM28*365 -> -396686.21
A31: *Note that these values are the AVERAGE of all simulations done for that load type
A32: *We can make more graphs and cost savings calculations with more filters (such as specific PV bus, specific PF, etc)
G33: Annualized % savings based on MW reduction by situation and bus
A34: Electricity rates | Ontario Energy Board | H34: Two small + 1 med | I34: 1 large | J34: 3 small | K34: Average
G35: Bus 4 | H35: =F29 -> -1621225.2 | I35: =O29 -> -2189434.9 | J35: =X29 -> -534364.64 | K35: =AVERAGE(H35:J35) -> -1448341.6
G36: Bus 9 | H36: =I29 -> -883576.17 | I36: =R29 -> -504523.84 | J36: =AA29 -> -602568.28 | K36: =AVERAGE(H36:J36) -> -663556.1
G37: Bus 14 | H37: =L29 -> -558147.66 | I37: =U29 -> -163537.36 | J37: =AD29 -> -468373.61 | K37: =AVERAGE(H37:J37) -> -396686.21
G38: Total | H38: =SUM(H35:H37) -> -3062949 | I38: =SUM(I35:I37) -> -2857496.1 | J38: =SUM(J35:J37) -> -1605306.5
G39: Average | H39: =AVERAGE(H38:J38) -> -2508583.9
H41: Two small + 1 med | I41: 1 large | J41: 3 small | K41: Average
G42: Bus 4 | H42: =H35/365 -> -4441.7129 | I42: =I35/365 -> -5998.4517 | J42: =J35/365 -> -1464.0127 | K42: =AVERAGE(H42:J42) -> -3968.0591
G43: Bus 9 | H43: =H36/365 -> -2420.7566 | I43: =I36/365 -> -1382.2571 | J43: =J36/365 -> -1650.872 | K43: =AVERAGE(H43:J43) -> -1817.9619
G44: Bus 14 | H44: =H37/365 -> -1529.1717 | I44: =I37/365 -> -448.04755 | J44: =J37/365 -> -1283.2154 | K44: =AVERAGE(H44:J44) -> -1086.8115
G45: Total | H45: =SUM(H42:H44) -> -8391.6411 | I45: =SUM(I42:I44) -> -7828.7563 | J45: =SUM(J42:J44) -> -4398.1001
G46: Average | H46: =AVERAGE(H45:J45) -> -6872.8325

Sheet IEEE 14-bus MW reduction data
A1: Situation | B1: Two small, 1 medium PV - SUNNY | E1: Two small, 1 medium PV - CLOUDY | H1: Two small, 1 medium PV - AVG | L1: One large PV - SUNNY | O1: One large PV - CLOUDY | R1: One large PV - AVG | U1: Three small PVs - SUNNY | X1: Three small PVs - Cloudy | AA1: Three small PVs - AVG
B2: % Reduction | E2: % Reduction | H2: % Reduction | K2: % Reduction | N2: % Reduction | Q2: % Reduction | T2: % Reduction | W2: % Reduction | Z2: % Reduction
A3: hour | B3: Bus 4 | C3: Bus 9 | D3: Bus 14 | E3: Bus 4 | F3: Bus 9 | G3: Bus 14 | H3: Bus 4 | I3: Bus 9 | J3: Bus 14 | K3: Bus 4 | L3: Bus 9 | M3: Bus 14 | N3: Bus 4 | O3: Bus 9 | P3: Bus 14 | Q3: Bus 4 | R3: Bus 9 | S3: Bus 14 | T3: Bus 4 | U3: Bus 9 | V3: Bus 14 | W3: Bus 4 | X3: Bus 9 | Y3: Bus 14 | Z3: Bus 4 | AA3: Bus 9 | AB3: Bus 14
A4: 1 | B4: -1.0922928 | C4: -0.63070107 | D4: -0.40576458 | E4: -1.0922928 | F4: -0.63070107 | G4: -0.40576458 | H4: =AVERAGE(B4,E4) -> -1.0922928 | I4: =AVERAGE(C4,F4) -> -0.63070107 | J4: =AVERAGE(D4,G4) -> -0.40576458 | K4: -1.7340508 | L4: -0.41671371 | M4: -0.13124752 | N4: -1.7340508 | O4: -0.41671371 | P4: -0.13124752 | Q4: =AVERAGE(K4,N4) -> -1.7340508 | R4: =AVERAGE(L4,O4) -> -0.41671371 | S4: =AVERAGE(M4,P4) -> -0.13124752 | T4: -0.38977051 | U4: -0.44854736 | V4: -0.34740257 | W4: -0.38977051 | X4: -0.44854736 | Y4: -0.34740257 | Z4: =AVERAGE(T4,W4) -> -0.38977051 | AA4: =AVERAGE(U4,X4) -> -0.44854736 | AB4: =AVERAGE(V4,Y4) -> -0.34740257
A5: 2 | B5: -1.0630608 | C5: -0.61417198 | D5: -0.39499569 | E5: -1.0630608 | F5: -0.61417198 | G5: -0.39499569 | H5: =AVERAGE(B5,E5) -> -1.0630608 | I5: =AVERAGE(C5,F5) -> -0.61417198 | J5: =AVERAGE(D5,G5) -> -0.39499569 | K5: -1.7135658 | L5: -0.41269302 | M5: -0.13017178 | N5: -1.7135658 | O5: -0.41269302 | P5: -0.13017178 | Q5: =AVERAGE(K5,N5) -> -1.7135658 | R5: =AVERAGE(L5,O5) -> -0.41269302 | S5: =AVERAGE(M5,P5) -> -0.13017178 | T5: -0.37919235 | U5: -0.4367466 | V5: -0.33810616 | W5: -0.37919235 | X5: -0.4367466 | Y5: -0.33810616 | Z5: =AVERAGE(T5,W5) -> -0.37919235 | AA5: =AVERAGE(U5,X5) -> -0.4367466 | AB5: =AVERAGE(V5,Y5) -> -0.33810616
A6: 3 | B6: -1.0434532 | C6: -0.60416031 | D6: -0.38877487 | E6: -1.0434532 | F6: -0.60416031 | G6: -0.38877487 | H6: =AVERAGE(B6,E6) -> -1.0434532 | I6: =AVERAGE(C6,F6) -> -0.60416031 | J6: =AVERAGE(D6,G6) -> -0.38877487 | K6: -1.6980247 | L6: -0.40924263 | M6: -0.1291151 | N6: -1.6980247 | O6: -0.40924263 | P6: -0.1291151 | Q6: =AVERAGE(K6,N6) -> -1.6980247 | R6: =AVERAGE(L6,O6) -> -0.40924263 | S6: =AVERAGE(M6,P6) -> -0.1291151 | T6: -0.36986923 | U6: -0.42936134 | V6: -0.33272171 | W6: -0.36986923 | X6: -0.42936134 | Y6: -0.33272171 | Z6: =AVERAGE(T6,W6) -> -0.36986923 | AA6: =AVERAGE(U6,X6) -> -0.42936134 | AB6: =AVERAGE(V6,Y6) -> -0.33272171
A7: 4 | B7: -1.0418587 | C7: -0.60334206 | D7: -0.38826752 | E7: -1.0418587 | F7: -0.60334206 | G7: -0.38826752 | H7: =AVERAGE(B7,E7) -> -1.0418587 | I7: =AVERAGE(C7,F7) -> -0.60334206 | J7: =AVERAGE(D7,G7) -> -0.38826752 | K7: -1.6967354 | L7: -0.40895653 | M7: -0.12902832 | N7: -1.6967354 | O7: -0.40895653 | P7: -0.12902832 | Q7: =AVERAGE(K7,N7) -> -1.6967354 | R7: =AVERAGE(L7,O7) -> -0.40895653 | S7: =AVERAGE(M7,P7) -> -0.12902832 | T7: -0.36910248 | U7: -0.42875862 | V7: -0.33228016 | W7: -0.36910248 | X7: -0.42875862 | Y7: -0.33228016 | Z7: =AVERAGE(T7,W7) -> -0.36910248 | AA7: =AVERAGE(U7,X7) -> -0.42875862 | AB7: =AVERAGE(V7,Y7) -> -0.33228016
A8: 5 | B8: -1.0702515 | C8: -0.61810493 | D8: -0.39751625 | E8: -1.0702515 | F8: -0.61810493 | G8: -0.39751625 | H8: =AVERAGE(B8,E8) -> -1.0702515 | I8: =AVERAGE(C8,F8) -> -0.61810493 | J8: =AVERAGE(D8,G8) -> -0.39751625 | K8: -1.718895 | L8: -0.41383362 | M8: -0.13051319 | N8: -1.718895 | O8: -0.41383362 | P8: -0.13051319 | Q8: =AVERAGE(K8,N8) -> -1.718895 | R8: =AVERAGE(L8,O8) -> -0.41383362 | S8: =AVERAGE(M8,P8) -> -0.13051319 | T8: -0.38206482 | U8: -0.43957138 | V8: -0.34027576 | W8: -0.38206482 | X8: -0.43957138 | Y8: -0.34027576 | Z8: =AVERAGE(T8,W8) -> -0.38206482 | AA8: =AVERAGE(U8,X8) -> -0.43957138 | AB8: =AVERAGE(V8,Y8) -> -0.34027576
A9: 6 | B9: -1.1311798 | C9: -0.65290451 | D9: -0.42031288 | E9: -1.1311798 | F9: -0.65290451 | G9: -0.42031288 | H9: =AVERAGE(B9,E9) -> -1.1311798 | I9: =AVERAGE(C9,F9) -> -0.65290451 | J9: =AVERAGE(D9,G9) -> -0.42031288 | K9: -1.7583847 | L9: -0.42201996 | M9: -0.13310814 | N9: -1.7583847 | O9: -0.42201996 | P9: -0.13310814 | Q9: =AVERAGE(K9,N9) -> -1.7583847 | R9: =AVERAGE(L9,O9) -> -0.42201996 | S9: =AVERAGE(M9,P9) -> -0.13310814 | T9: -0.40315628 | U9: -0.46429443 | V9: -0.35992908 | W9: -0.40315628 | X9: -0.46429443 | Y9: -0.35992908 | Z9: =AVERAGE(T9,W9) -> -0.40315628 | AA9: =AVERAGE(U9,X9) -> -0.46429443 | AB9: =AVERAGE(V9,Y9) -> -0.35992908
A10: 7 | B10: -1.263298 | C10: -0.71513367 | D10: -0.45750618 | E10: -1.2661743 | F10: -0.71675301 | G10: -0.458498 | H10: =AVERAGE(B10,E10) -> -1.2647362 | I10: =AVERAGE(C10,F10) -> -0.71594334 | J10: =AVERAGE(D10,G10) -> -0.45800209 | K10: -1.8033867 | L10: -0.43034172 | M10: -0.13557529 | N10: -1.8033867 | O10: -0.43034172 | P10: -0.13557529 | Q10: =AVERAGE(K10,N10) -> -1.8033867 | R10: =AVERAGE(L10,O10) -> -0.43034172 | S10: =AVERAGE(M10,P10) -> -0.13557529 | T10: -0.43422318 | U10: -0.50060844 | V10: -0.38892078 | W10: -0.43484497 | X10: -0.50163078 | Y10: -0.38971996 | Z10: =AVERAGE(T10,W10) -> -0.43453407 | AA10: =AVERAGE(U10,X10) -> -0.50111961 | AB10: =AVERAGE(V10,Y10) -> -0.38932037
A11: 8 | B11: -1.3543167 | C11: -0.74637985 | D11: -0.47307301 | E11: -1.3965988 | F11: -0.7701683 | G11: -0.48766708 | H11: =AVERAGE(B11,E11) -> -1.3754578 | I11: =AVERAGE(C11,F11) -> -0.75827408 | J11: =AVERAGE(D11,G11) -> -0.48037004 | K11: -1.823288 | L11: -0.43325424 | M11: -0.13638115 | N11: -1.823288 | O11: -0.43325424 | P11: -0.13638115 | Q11: =AVERAGE(K11,N11) -> -1.823288 | R11: =AVERAGE(L11,O11) -> -0.43325424 | S11: =AVERAGE(M11,P11) -> -0.13638115 | T11: -0.44696426 | U11: -0.51169586 | V11: -0.39805889 | W11: -0.45617676 | X11: -0.52674866 | Y11: -0.40981865 | Z11: =AVERAGE(T11,W11) -> -0.45157051 | AA11: =AVERAGE(U11,X11) -> -0.51922226 | AB11: =AVERAGE(V11,Y11) -> -0.40393877
A12: 9 | B12: -1.2727585 | C12: -0.6945076 | D12: -0.44013977 | E12: -1.4346771 | F12: -0.78555107 | G12: -0.49600315 | H12: =AVERAGE(B12,E12) -> -1.3537178 | I12: =AVERAGE(C12,F12) -> -0.74002934 | J12: =AVERAGE(D12,G12) -> -0.46807146 | K12: -1.8273048 | L12: -0.43366623 | M12: -0.13648701 | N12: -1.8273048 | O12: -0.43366241 | P12: -0.13647652 | Q12: =AVERAGE(K12,N12) -> -1.8273048 | R12: =AVERAGE(L12,O12) -> -0.43366432 | S12: =AVERAGE(M12,P12) -> -0.13648176 | T12: -0.4269371 | U12: -0.47620964 | V12: -0.37048721 | W12: -0.46223068 | X12: -0.5338726 | Y12: -0.41552925 | Z12: =AVERAGE(T12,W12) -> -0.44458389 | AA12: =AVERAGE(U12,X12) -> -0.50504112 | AB12: =AVERAGE(V12,Y12) -> -0.39300823
A13: 10 | B13: -1.1240616 | C13: -0.60855484 | D13: -0.38696098 | E13: -1.4485893 | F13: -0.79090691 | G13: -0.49883652 | H13: =AVERAGE(B13,E13) -> -1.2863255 | I13: =AVERAGE(C13,F13) -> -0.69973087 | J13: =AVERAGE(D13,G13) -> -0.44289875 | K13: -1.8287201 | L13: -0.43335915 | M13: -0.1361227 | N13: -1.8287201 | O13: -0.43377686 | P13: -0.13650131 | Q13: =AVERAGE(K13,N13) -> -1.8287201 | R13: =AVERAGE(L13,O13) -> -0.433568 | S13: =AVERAGE(M13,P13) -> -0.13631201 | T13: -0.39347839 | U13: -0.42051697 | V13: -0.32707977 | W13: -0.46433258 | X13: -0.53618431 | Y13: -0.41739559 | Z13: =AVERAGE(T13,W13) -> -0.42890549 | AA13: =AVERAGE(U13,X13) -> -0.47835064 | AB13: =AVERAGE(V13,Y13) -> -0.37223768
A14: 11 | B14: -0.96829224 | C14: -0.51965714 | D14: -0.33215809 | E14: -1.4537811 | F14: -0.79225349 | G14: -0.49936485 | H14: =AVERAGE(B14,E14) -> -1.2110367 | I14: =AVERAGE(C14,F14) -> -0.65595531 | J14: =AVERAGE(D14,G14) -> -0.41576147 | K14: -1.7959824 | L14: -0.42515373 | M14: -0.13378811 | N14: -1.8295517 | O14: -0.43383217 | P14: -0.13650894 | Q14: =AVERAGE(K14,N14) -> -1.812767 | R14: =AVERAGE(L14,O14) -> -0.42949295 | S14: =AVERAGE(M14,P14) -> -0.13514853 | T14: -0.35876846 | U14: -0.36322212 | V14: -0.28244209 | W14: -0.46486282 | X14: -0.53634644 | Y14: -0.41755867 | Z14: =AVERAGE(T14,W14) -> -0.41181564 | AA14: =AVERAGE(U14,X14) -> -0.44978428 | AB14: =AVERAGE(V14,Y14) -> -0.35000038
A15: 12 | B15: -0.8855896 | C15: -0.47169113 | D15: -0.30242825 | E15: -1.4589729 | F15: -0.79357719 | G15: -0.49988651 | H15: =AVERAGE(B15,E15) -> -1.1722813 | I15: =AVERAGE(C15,F15) -> -0.63263416 | J15: =AVERAGE(D15,G15) -> -0.40115738 | K15: -1.6390419 | L15: -0.38438988 | M15: -0.12095547 | N15: -1.8303337 | O15: -0.43387222 | P15: -0.13651752 | Q15: =AVERAGE(K15,N15) -> -1.7346878 | R15: =AVERAGE(L15,O15) -> -0.40913105 | S15: =AVERAGE(M15,P15) -> -0.1287365 | T15: -0.33992386 | U15: -0.33183098 | V15: -0.25801849 | W15: -0.46538162 | X15: -0.53649902 | Y15: -0.41770935 | Z15: =AVERAGE(T15,W15) -> -0.40265274 | AA15: =AVERAGE(U15,X15) -> -0.434165 | AB15: =AVERAGE(V15,Y15) -> -0.33786392
... A27: 24 | B27: -1.1399803 | C27: -0.65792274 | D27: -0.42360687 | E27: -1.1399803 | F27: -0.65792274 | G27: -0.42360687 | H27: =AVERAGE(B27,E27) -> -1.1399803 | I27: =AVERAGE(C27,F27) -> -0.65792274 | J27: =AVERAGE(D27,G27) -> -0.42360687 | K27: -1.7634506 | L27: -0.42301178 | M27: -0.1334095 | N27: -1.7634506 | O27: -0.42301178 | P27: -0.1334095 | Q27: =AVERAGE(K27,N27) -> -1.7634506 | R27: =AVERAGE(L27,O27) -> -0.42301178 | S27: =AVERAGE(M27,P27) -> -0.1334095 | T27: -0.40618896 | U27: -0.46785164 | V27: -0.36276913 | W27: -0.40618896 | X27: -0.46785164 | Y27: -0.36276913 | Z27: =AVERAGE(T27,W27) -> -0.40618896 | AA27: =AVERAGE(U27,X27) -> -0.46785164 | AB27: =AVERAGE(V27,Y27) -> -0.36276913

Sheet IEEE 14-bus % reduction data
A1: Situation | B1: Two small, 1 medium PV - SUNNY | E1: Two small, 1 medium PV - CLOUDY | H1: Two small, 1 medium PV - AVG | L1: One large PV - SUNNY | O1: One large PV - CLOUDY | R1: One large PV - AVG | U1: Three small PVs - SUNNY | X1: Three small PVs - Cloudy | AA1: Three small PVs - AVG | AC1: Overall Average
B2: % Reduction | E2: % Reduction | H2: % Reduction | K2: % Reduction | N2: % Reduction | Q2: % Reduction | T2: % Reduction | W2: % Reduction | Z2: % Reduction | AC2: % Reduction
A3: hour | B3: Bus 4 | C3: Bus 9 | D3: Bus 14 | E3: Bus 4 | F3: Bus 9 | G3: Bus 14 | H3: Bus 4 | I3: Bus 9 | J3: Bus 14 | K3: Bus 4 | L3: Bus 9 | M3: Bus 14 | N3: Bus 4 | O3: Bus 9 | P3: Bus 14 | Q3: Bus 4 | R3: Bus 9 | S3: Bus 14 | T3: Bus 4 | U3: Bus 9 | V3: Bus 14 | W3: Bus 4 | X3: Bus 9 | Y3: Bus 14 | Z3: Bus 4 | AA3: Bus 9 | AB3: Bus 14 | AC3: Bus 4 | AD3: Bus 9 | AE3: Bus 14
A4: 1 | B4: -0.029615491 | C4: -0.027708266 | D4: -0.035293576 | E4: -0.029615491 | F4: -0.027708266 | G4: -0.035293576 | H4: =AVERAGE(B4,E4) -> -0.029615491 | I4: =AVERAGE(C4,F4) -> -0.027708266 | J4: =AVERAGE(D4,G4) -> -0.035293576 | K4: -0.047015567 | L4: -0.018307269 | M4: -0.011415965 | N4: -0.047015567 | O4: -0.018307269 | P4: -0.011415965 | Q4: =AVERAGE(K4,N4) -> -0.047015567 | R4: =AVERAGE(L4,O4) -> -0.018307269 | S4: =AVERAGE(M4,P4) -> -0.011415965 | T4: -0.010567904 | U4: -0.019705801 | V4: -0.030217224 | W4: -0.010567904 | X4: -0.019705801 | Y4: -0.030217224 | Z4: =AVERAGE(T4,W4) -> -0.010567904 | AA4: =AVERAGE(U4,X4) -> -0.019705801 | AB4: =AVERAGE(V4,Y4) -> -0.030217224 | AC4: =AVERAGE(H4,Q4,Z4) -> -0.029066321 | AD4: =AVERAGE(I4,R4,AA4) -> -0.021907112 | AE4: =AVERAGE(J4,S4,AB4) -> -0.025642255
A5: 2 | B5: -0.029585959 | C5: -0.027696407 | D5: -0.035266434 | E5: -0.029585959 | F5: -0.027696407 | G5: -0.035266434 | H5: =AVERAGE(B5,E5) -> -0.029585959 | I5: =AVERAGE(C5,F5) -> -0.027696407 | J5: =AVERAGE(D5,G5) -> -0.035266434 | K5: -0.047690113 | L5: -0.018610608 | M5: -0.011622138 | N5: -0.047690113 | O5: -0.018610608 | P5: -0.011622138 | Q5: =AVERAGE(K5,N5) -> -0.047690113 | R5: =AVERAGE(L5,O5) -> -0.018610608 | S5: =AVERAGE(M5,P5) -> -0.011622138 | T5: -0.010553272 | U5: -0.019695317 | V5: -0.030187161 | W5: -0.010553272 | X5: -0.019695317 | Y5: -0.030187161 | Z5: =AVERAGE(T5,W5) -> -0.010553272 | AA5: =AVERAGE(U5,X5) -> -0.019695317 | AB5: =AVERAGE(V5,Y5) -> -0.030187161 | AC5: =AVERAGE(H5,Q5,Z5) -> -0.029276448 | AD5: =AVERAGE(I5,R5,AA5) -> -0.022000777 | AE5: =AVERAGE(J5,S5,AB5) -> -0.025691911
A6: 3 | B6: -0.029471534 | C6: -0.027649534 | D6: -0.035226505 | E6: -0.029471534 | F6: -0.027649534 | G6: -0.035226505 | H6: =AVERAGE(B6,E6) -> -0.029471534 | I6: =AVERAGE(C6,F6) -> -0.027649534 | J6: =AVERAGE(D6,G6) -> -0.035226505 | K6: -0.047959403 | L6: -0.018729082 | M6: -0.011698991 | N6: -0.047959403 | O6: -0.018729082 | P6: -0.011698991 | Q6: =AVERAGE(K6,N6) -> -0.047959403 | R6: =AVERAGE(L6,O6) -> -0.018729082 | S6: =AVERAGE(M6,P6) -> -0.011698991 | T6: -0.010446672 | U6: -0.019649819 | V6: -0.030147584 | W6: -0.010446672 | X6: -0.019649819 | Y6: -0.030147584 | Z6: =AVERAGE(T6,W6) -> -0.010446672 | AA6: =AVERAGE(U6,X6) -> -0.019649819 | AB6: =AVERAGE(V6,Y6) -> -0.030147584 | AC6: =AVERAGE(H6,Q6,Z6) -> -0.029292536 | AD6: =AVERAGE(I6,R6,AA6) -> -0.022009478 | AE6: =AVERAGE(J6,S6,AB6) -> -0.025691027
A7: 4 | B7: -0.029462297 | C7: -0.027645678 | D7: -0.035223335 | E7: -0.029462297 | F7: -0.027645678 | G7: -0.035223335 | H7: =AVERAGE(B7,E7) -> -0.029462297 | I7: =AVERAGE(C7,F7) -> -0.027645678 | J7: =AVERAGE(D7,G7) -> -0.035223335 | K7: -0.047981289 | L7: -0.018738758 | M7: -0.011705351 | N7: -0.047981289 | O7: -0.018738758 | P7: -0.011705351 | Q7: =AVERAGE(K7,N7) -> -0.047981289 | R7: =AVERAGE(L7,O7) -> -0.018738758 | S7: =AVERAGE(M7,P7) -> -0.011705351 | T7: -0.010437699 | U7: -0.019646107 | V7: -0.030144204 | W7: -0.010437699 | X7: -0.019646107 | Y7: -0.030144204 | Z7: =AVERAGE(T7,W7) -> -0.010437699 | AA7: =AVERAGE(U7,X7) -> -0.019646107 | AB7: =AVERAGE(V7,Y7) -> -0.030144204 | AC7: =AVERAGE(H7,Q7,Z7) -> -0.029293762 | AD7: =AVERAGE(I7,R7,AA7) -> -0.022010181 | AE7: =AVERAGE(J7,S7,AB7) -> -0.025690963
A8: 5 | B8: -0.029604917 | C8: -0.02770423 | D8: -0.035275608 | E8: -0.029604917 | F8: -0.02770423 | G8: -0.035275608 | H8: =AVERAGE(B8,E8) -> -0.029604917 | I8: =AVERAGE(C8,F8) -> -0.02770423 | J8: =AVERAGE(D8,G8) -> -0.035275608 | K8: -0.047547464 | L8: -0.018548536 | M8: -0.011581746 | N8: -0.047547464 | O8: -0.018548536 | P8: -0.011581746 | Q8: =AVERAGE(K8,N8) -> -0.047547464 | R8: =AVERAGE(L8,O8) -> -0.018548536 | S8: =AVERAGE(M8,P8) -> -0.011581746 | T8: -0.010568542 | U8: -0.019702135 | V8: -0.030196085 | W8: -0.010568542 | X8: -0.019702135 | Y8: -0.030196085 | Z8: =AVERAGE(T8,W8) -> -0.010568542 | AA8: =AVERAGE(U8,X8) -> -0.019702135 | AB8: =AVERAGE(V8,Y8) -> -0.030196085 | AC8: =AVERAGE(H8,Q8,Z8) -> -0.029240308 | AD8: =AVERAGE(I8,R8,AA8) -> -0.021984967 | AE8: =AVERAGE(J8,S8,AB8) -> -0.025684479
A9: 6 | B9: -0.029632919 | C9: -0.027713944 | D9: -0.035322962 | E9: -0.029632919 | F9: -0.027713944 | G9: -0.035322962 | H9: =AVERAGE(B9,E9) -> -0.029632919 | I9: =AVERAGE(C9,F9) -> -0.027713944 | J9: =AVERAGE(D9,G9) -> -0.035322962 | K9: -0.046063474 | L9: -0.01791355 | M9: -0.011186366 | N9: -0.046063474 | O9: -0.01791355 | P9: -0.011186366 | Q9: =AVERAGE(K9,N9) -> -0.046063474 | R9: =AVERAGE(L9,O9) -> -0.01791355 | S9: =AVERAGE(M9,P9) -> -0.011186366 | T9: -0.010561272 | U9: -0.019707981 | V9: -0.030248327 | W9: -0.010561272 | X9: -0.019707981 | Y9: -0.030248327 | Z9: =AVERAGE(T9,W9) -> -0.010561272 | AA9: =AVERAGE(U9,X9) -> -0.019707981 | AB9: =AVERAGE(V9,Y9) -> -0.030248327 | AC9: =AVERAGE(H9,Q9,Z9) -> -0.028752555 | AD9: =AVERAGE(I9,R9,AA9) -> -0.021778492 | AE9: =AVERAGE(J9,S9,AB9) -> -0.025585885
A10: 7 | B10: -0.030638568 | C10: -0.028103202 | D10: -0.035596003 | E10: -0.030708326 | F10: -0.028166838 | G10: -0.035673171 | H10: =AVERAGE(B10,E10) -> -0.030673447 | I10: =AVERAGE(C10,F10) -> -0.02813502 | J10: =AVERAGE(D10,G10) -> -0.035634587 | K10: -0.043737253 | L10: -0.016911496 | M10: -0.010548357 | N10: -0.043737253 | O10: -0.016911496 | P10: -0.010548357 | Q10: =AVERAGE(K10,N10) -> -0.043737253 | R10: =AVERAGE(L10,O10) -> -0.016911496 | S10: =AVERAGE(M10,P10) -> -0.010548357 | T10: -0.010531146 | U10: -0.019672826 | V10: -0.030259756 | W10: -0.010546226 | X10: -0.019713002 | Y10: -0.030321936 | Z10: =AVERAGE(T10,W10) -> -0.010538686 | AA10: =AVERAGE(U10,X10) -> -0.019692914 | AB10: =AVERAGE(V10,Y10) -> -0.030290846 | AC10: =AVERAGE(H10,Q10,Z10) -> -0.028316462 | AD10: =AVERAGE(I10,R10,AA10) -> -0.02157981 | AE10: =AVERAGE(J10,S10,AB10) -> -0.025491263
A11: 8 | B11: -0.031276062 | C11: -0.027929146 | D11: -0.035047872 | E11: -0.032252509 | F11: -0.028819297 | G11: -0.036129082 | H11: =AVERAGE(B11,E11) -> -0.031764286 | I11: =AVERAGE(C11,F11) -> -0.028374222 | J11: =AVERAGE(D11,G11) -> -0.035588477 | K11: -0.042106302 | L11: -0.016212148 | M11: -0.010103872 | N11: -0.042106302 | O11: -0.016212148 | P11: -0.010103872 | Q11: =AVERAGE(K11,N11) -> -0.042106302 | R11: =AVERAGE(L11,O11) -> -0.016212148 | S11: =AVERAGE(M11,P11) -> -0.010103872 | T11: -0.010322019 | U11: -0.019147393 | V11: -0.02949041 | W11: -0.010534768 | X11: -0.019710661 | Y11: -0.030361638 | Z11: =AVERAGE(T11,W11) -> -0.010428393 | AA11: =AVERAGE(U11,X11) -> -0.019429027 | AB11: =AVERAGE(V11,Y11) -> -0.029926024 | AC11: =AVERAGE(H11,Q11,Z11) -> -0.02809966 | AD11: =AVERAGE(I11,R11,AA11) -> -0.021338466 | AE11: =AVERAGE(J11,S11,AB11) -> -0.025206124
A12: 9 | B12: -0.02900201 | C12: -0.025642772 | D12: -0.032174688 | E12: -0.032691607 | F12: -0.0290043 | G12: -0.036258361 | H12: =AVERAGE(B12,E12) -> -0.030846809 | I12: =AVERAGE(C12,F12) -> -0.027323536 | J12: =AVERAGE(D12,G12) -> -0.034216525 | K12: -0.041638311 | L12: -0.016011926 | M12: -0.0099773462 | N12: -0.041638311 | O12: -0.016011785 | P12: -0.0099765794 | Q12: =AVERAGE(K12,N12) -> -0.041638311 | R12: =AVERAGE(L12,O12) -> -0.016011855 | S12: =AVERAGE(M12,P12) -> -0.0099769628 | T12: -0.0097285026 | U12: -0.017582724 | V12: -0.027083012 | W12: -0.010532728 | X12: -0.019711769 | Y12: -0.030375633 | Z12: =AVERAGE(T12,W12) -> -0.010130615 | AA12: =AVERAGE(U12,X12) -> -0.018647246 | AB12: =AVERAGE(V12,Y12) -> -0.028729322 | AC12: =AVERAGE(H12,Q12,Z12) -> -0.027538578 | AD12: =AVERAGE(I12,R12,AA12) -> -0.020660879 | AE12: =AVERAGE(J12,S12,AB12) -> -0.024307603
A13: 10 | B13: -0.025477717 | C13: -0.02234992 | D13: -0.02813709 | E13: -0.032833387 | F13: -0.029047022 | G13: -0.036271895 | H13: =AVERAGE(B13,E13) -> -0.029155552 | I13: =AVERAGE(C13,F13) -> -0.025698471 | J13: =AVERAGE(D13,G13) -> -0.032204493 | K13: -0.041449342 | L13: -0.015915644 | M13: -0.0098978888 | N13: -0.041449342 | O13: -0.015930985 | P13: -0.0099254186 | Q13: =AVERAGE(K13,N13) -> -0.041449342 | R13: =AVERAGE(L13,O13) -> -0.015923314 | S13: =AVERAGE(M13,P13) -> -0.0099116537 | T13: -0.0089184892 | U13: -0.015443999 | V13: -0.023782948 | W13: -0.010524454 | X13: -0.019692024 | Y13: -0.030350082 | Z13: =AVERAGE(T13,W13) -> -0.0097214714 | AA13: =AVERAGE(U13,X13) -> -0.017568011 | AB13: =AVERAGE(V13,Y13) -> -0.027066515 | AC13: =AVERAGE(H13,Q13,Z13) -> -0.026775455 | AD13: =AVERAGE(I13,R13,AA13) -> -0.019729932 | AE13: =AVERAGE(J13,S13,AB13) -> -0.023060887
A14: 11 | B14: -0.021873621 | C14: -0.01902116 | D14: -0.024071364 | E14: -0.032840765 | F14: -0.028999083 | G14: -0.036188772 | H14: =AVERAGE(B14,E14) -> -0.027357193 | I14: =AVERAGE(C14,F14) -> -0.024010121 | J14: =AVERAGE(D14,G14) -> -0.030130068 | K14: -0.040571055 | L14: -0.015562024 | M14: -0.0096955709 | N14: -0.041329383 | O14: -0.015879684 | P14: -0.0098927486 | Q14: =AVERAGE(K14,N14) -> -0.040950219 | R14: =AVERAGE(L14,O14) -> -0.015720854 | S14: =AVERAGE(M14,P14) -> -0.0097941598 | T14: -0.0081045424 | U14: -0.013295124 | V14: -0.020468466 | W14: -0.010501203 | X14: -0.019632043 | Y14: -0.03026031 | Z14: =AVERAGE(T14,W14) -> -0.0093028727 | AA14: =AVERAGE(U14,X14) -> -0.016463583 | AB14: =AVERAGE(V14,Y14) -> -0.025364388 | AC14: =AVERAGE(H14,Q14,Z14) -> -0.025870095 | AD14: =AVERAGE(I14,R14,AA14) -> -0.01873152 | AE14: =AVERAGE(J14,S14,AB14) -> -0.021762872
A15: 12 | B15: -0.019938634 | C15: -0.017207844 | D15: -0.021843733 | E15: -0.032848091 | F15: -0.028950624 | G15: -0.036105714 | H15: =AVERAGE(B15,E15) -> -0.026393363 | I15: =AVERAGE(C15,F15) -> -0.023079234 | J15: =AVERAGE(D15,G15) -> -0.028974724 | K15: -0.036902259 | L15: -0.014022992 | M15: -0.0087363499 | N15: -0.041209105 | O15: -0.015828166 | P15: -0.0098603635 | Q15: =AVERAGE(K15,N15) -> -0.039055682 | R15: =AVERAGE(L15,O15) -> -0.014925579 | S15: =AVERAGE(M15,P15) -> -0.0092983567 | T15: -0.0076532262 | U15: -0.012105582 | V15: -0.018636114 | W15: -0.010477849 | X15: -0.019572112 | Y15: -0.030170237 | Z15: =AVERAGE(T15,W15) -> -0.0090655376 | AA15: =AVERAGE(U15,X15) -> -0.015838847 | AB15: =AVERAGE(V15,Y15) -> -0.024403175 | AC15: =AVERAGE(H15,Q15,Z15) -> -0.024838194 | AD15: =AVERAGE(I15,R15,AA15) -> -0.017947887 | AE15: =AVERAGE(J15,S15,AB15) -> -0.020892085
... A27: 24 | B27: -0.029637082 | C27: -0.027715256 | D27: -0.035329925 | E27: -0.029637082 | F27: -0.027715256 | G27: -0.035329925 | H27: =AVERAGE(B27,E27) -> -0.029637082 | I27: =AVERAGE(C27,F27) -> -0.027715256 | J27: =AVERAGE(D27,G27) -> -0.035329925 | K27: -0.045845995 | L27: -0.017819539 | M27: -0.011126703 | N27: -0.045845995 | O27: -0.017819539 | P27: -0.011126703 | Q27: =AVERAGE(K27,N27) -> -0.045845995 | R27: =AVERAGE(L27,O27) -> -0.017819539 | S27: =AVERAGE(M27,P27) -> -0.011126703 | T27: -0.010560056 | U27: -0.019708435 | V27: -0.030255897 | W27: -0.010560056 | X27: -0.019708435 | Y27: -0.030255897 | Z27: =AVERAGE(T27,W27) -> -0.010560056 | AA27: =AVERAGE(U27,X27) -> -0.019708435 | AB27: =AVERAGE(V27,Y27) -> -0.030255897 | AC27: =AVERAGE(H27,Q27,Z27) -> -0.028681044 | AD27: =AVERAGE(I27,R27,AA27) -> -0.021747743 | AE27: =AVERAGE(J27,S27,AB27) -> -0.025570842
AB28: Average | AC28: =AVERAGE(AC4:AC27) -> -0.027793343 | AD28: =AVERAGE(AD4:AD27) -> -0.0208404 | AE28: =AVERAGE(AE4:AE27) -> -0.024476348 | AF28: =AVERAGE(AC28:AE28) -> -0.024370031
B32: Avg for 2 small + 1 med combo | E32: 0.04 | F32: 0.09 | G32: 0.14
B33: =AVERAGE(B4:J27) -> -0.030767333 | E33: =AVERAGE(B4:B27,E4:E27,H4:H27) -> -0.030643043 | F33: =AVERAGE(C4:C27,F4:F27,I4:I27) -> -0.027344655 | G33: =AVERAGE(D4:D27,G4:G27,J4:J26) -> -0.034299998 | S33: =AVERAGE(T4:T27,W4:W27,Z4:Z27) -> -0.010219975 | T33: =AVERAGE(U4:U27,X4:X27,AA4:AA27) -> -0.018784398 | U33: =AVERAGE(V4:V27,Y4:Y27,AB4:AB27) -> -0.028897088
